LICENSE
README.md
setup.py
gaupy/Binomialdistribution.py
gaupy/Gaussiandistribution.py
gaupy/Generaldistribution.py
gaupy/__init__.py
gaupy.egg-info/PKG-INFO
gaupy.egg-info/SOURCES.txt
gaupy.egg-info/dependency_links.txt
gaupy.egg-info/not-zip-safe
gaupy.egg-info/top_level.txt