Metadata-Version: 2.1
Name: gaupy
Version: 1.0
Summary: Gaussian and Binomial distributions
Author: Victor Pontello
Author-email: vpontello@outlook.com
License: UNKNOWN
Platform: UNKNOWN
License-File: LICENSE
